yi_config_starter/__init__.py
yi_config_starter/config_starter.py
yi_config_starter-0.1.3.dist-info/licenses/LICENSE
yi_config_starter-0.1.3.dist-info/METADATA
yi_config_starter-0.1.3.dist-info/WHEEL
yi_config_starter-0.1.3.dist-info/top_level.txt
yi_config_starter-0.1.3.dist-info/RECORD
