Metadata-Version: 2.4
Name: yi-config-starter
Version: 0.1.3
Summary: Config starter for my local projects
Author: Yunus Indori
License: MIT License
Requires-Python: >=3.9
License-File: LICENSE
Requires-Dist: PyYAML>=6.0
Dynamic: license-file
